QuantExt/QuantExt.py
QuantExt/_QuantExt.cp37-win_amd64.pyd
QuantExt/__init__.py
QuantExt_Python-1.8.3.3.5.dist-info/METADATA
QuantExt_Python-1.8.3.3.5.dist-info/WHEEL
QuantExt_Python-1.8.3.3.5.dist-info/top_level.txt
QuantExt_Python-1.8.3.3.5.dist-info/RECORD
