Metadata-Version: 2.1
Name: QuantExt-Python
Version: 1.8.3.3.5
Summary: Python bindings for the QuantExt library
Home-page: http://quternion.com
Author: Quaternion Risk Management
Author-email: info@quaternion.com
License: ORE-SWIG is
